{"cameraMode":{"drawMode":0,"name":"Shaded","section":"Shading Mode"},"sceneLighting":true,"audioPlay":false,"sceneViewState":{"m_AlwaysRefresh":false,"showFog":true,"showSkybox":true,"showFlares":true,"showImageEffects":true,"showParticleSystems":true,"showVisualEffectGraphs":true,"m_FxEnabled":true},"in2DMode":false,"pivot":{"x":2.7520947456359865,"y":0.5088860988616943,"z":2.3861277103424074},"rotation":{"x":-0.27843302488327029,"y":-0.03142312914133072,"z":0.009103531949222088,"w":-0.9599226117134094},"size":3.007854700088501,"orthographic":false}